MANIFEST.in
README.rst
setup.py
version.txt
micral_core/__init__.py
micral_core/micral_core.py
micral_core/version.txt
micral_core.egg-info/PKG-INFO
micral_core.egg-info/SOURCES.txt
micral_core.egg-info/dependency_links.txt
micral_core.egg-info/not-zip-safe
micral_core.egg-info/requires.txt
micral_core.egg-info/top_level.txt